rlm/__init__.py
rlm/py.typed
rlm/agent_lib/__init__.py
rlm/agent_lib/boot.py
rlm/agent_lib/context.py
rlm/agent_lib/utils.py
rlm/config/__init__.py
rlm/config/settings.py
rlm/core/__init__.py
rlm/core/exceptions.py
rlm/core/orchestrator.py
rlm/core/parsing.py
rlm/core/memory/__init__.py
rlm/core/memory/handle.py
rlm/core/repl/__init__.py
rlm/core/repl/async_docker.py
rlm/core/repl/docker.py
rlm/data/pricing.json
rlm/llm/__init__.py
rlm/llm/anthropic_client.py
rlm/llm/base.py
rlm/llm/factory.py
rlm/llm/google_client.py
rlm/llm/openai_client.py
rlm/prompt_templates/__init__.py
rlm/prompt_templates/system.py
rlm/security/__init__.py
rlm/security/egress.py
rlm/utils/__init__.py
rlm/utils/cost.py
rlm_python-2.1.0.dist-info/METADATA
rlm_python-2.1.0.dist-info/WHEEL
rlm_python-2.1.0.dist-info/entry_points.txt
rlm_python-2.1.0.dist-info/licenses/LICENSE
rlm_python-2.1.0.dist-info/RECORD
