Metadata-Version: 2.4
Name: rlm-python
Version: 2.1.0
Summary: Secure LLM-driven code execution with Docker sandboxing
Project-URL: Homepage, https://github.com/rlm-python/rlm
Project-URL: Documentation, https://rlm-python.readthedocs.io
Project-URL: Repository, https://github.com/rlm-python/rlm
Project-URL: Issues, https://github.com/rlm-python/rlm/issues
Author-email: RLM Team <team@rlm.dev>
License-Expression: MIT
License-File: LICENSE
Keywords: agent,ai,code-execution,docker,llm,sandbox,security
Classifier: Development Status :: 4 - Beta
Classifier: Intended Audience :: Developers
Classifier: License :: OSI Approved :: MIT License
Classifier: Operating System :: OS Independent
Classifier: Programming Language :: Python :: 3
Classifier: Programming Language :: Python :: 3.10
Classifier: Programming Language :: Python :: 3.11
Classifier: Programming Language :: Python :: 3.12
Classifier: Topic :: Security
Classifier: Topic :: Software Development :: Libraries :: Python Modules
Classifier: Typing :: Typed
Requires-Python: >=3.10
Requires-Dist: aiodocker>=0.21.0
Requires-Dist: anthropic>=0.18.0
Requires-Dist: docker>=7.0.0
Requires-Dist: google-generativeai>=0.4.0
Requires-Dist: mistletoe>=1.2.0
Requires-Dist: openai>=1.0.0
Requires-Dist: pydantic-settings>=2.1.0
Requires-Dist: pydantic>=2.5.0
Provides-Extra: dev
Requires-Dist: mypy>=1.8.0; extra == 'dev'
Requires-Dist: pip-audit>=2.6.0; extra == 'dev'
Requires-Dist: pytest-asyncio>=0.21.0; extra == 'dev'
Requires-Dist: pytest-cov>=4.1.0; extra == 'dev'
Requires-Dist: pytest>=7.4.0; extra == 'dev'
Requires-Dist: ruff>=0.1.0; extra == 'dev'
Requires-Dist: types-docker>=7.0.0; extra == 'dev'
